pangeo_forge_cordex/__init__.py
pangeo_forge_cordex/_version.py
pangeo_forge_cordex/catalog.py
pangeo_forge_cordex/esgf_access.py
pangeo_forge_cordex/parsing.py
pangeo_forge_cordex/recipe.py
pangeo_forge_cordex/utils.py
tests/__init__.py
tests/test_parsing.py
tests/test_recipe_creation.py
pangeo_forge_cordex-0.3.4.dist-info/LICENSE
pangeo_forge_cordex-0.3.4.dist-info/METADATA
pangeo_forge_cordex-0.3.4.dist-info/WHEEL
pangeo_forge_cordex-0.3.4.dist-info/top_level.txt
pangeo_forge_cordex-0.3.4.dist-info/RECORD
