Metadata-Version: 2.1
Name: pangeo-forge-cordex
Version: 0.3.4
Summary: "Using queries to the ESGF API to generate urls and keyword arguments for receipe generation in pangeo-forge"
Home-page: https://github.com/euro-cordex/pangeo-forge-cordex
Maintainer: Lars Buntemeyer
Maintainer-email: lars.buntemeyer@hereon.de
License: MIT
Keywords: pangeo,data,esgf
Classifier: Development Status :: 1 - Planning
Classifier: License :: OSI Approved :: MIT License
Classifier: Operating System :: OS Independent
Classifier: Intended Audience :: Science/Research
Classifier: Programming Language :: Python
Classifier: Programming Language :: Python :: 3
Classifier: Programming Language :: Python :: 3.9
Classifier: Programming Language :: Python :: 3.10
Classifier: Programming Language :: Python :: 3.11
Classifier: Topic :: Scientific/Engineering
Requires-Python: >=3.9
License-File: LICENSE
Requires-Dist: aiohttp
Requires-Dist: requests
